qcloud_cos/__init__.py
qcloud_cos/ai_recognition.py
qcloud_cos/cos_auth.py
qcloud_cos/cos_client.py
qcloud_cos/cos_comm.py
qcloud_cos/cos_encryption_client.py
qcloud_cos/cos_exception.py
qcloud_cos/cos_threadpool.py
qcloud_cos/cos_vectors_client.py
qcloud_cos/crypto.py
qcloud_cos/intelligent_speech.py
qcloud_cos/meta_insight.py
qcloud_cos/resumable_downloader.py
qcloud_cos/select_event_stream.py
qcloud_cos/streambody.py
qcloud_cos/version.py
qcloud_cos/xml2dict.py
cos_python_sdk_v5-1.9.41.dist-info/LICENSE
cos_python_sdk_v5-1.9.41.dist-info/METADATA
cos_python_sdk_v5-1.9.41.dist-info/WHEEL
cos_python_sdk_v5-1.9.41.dist-info/top_level.txt
cos_python_sdk_v5-1.9.41.dist-info/RECORD
