Metadata-Version: 2.1
Name: cos-python-sdk-v5
Version: 1.9.41
Summary: cos-python-sdk-v5
Home-page: https://www.qcloud.com/
Author: tiedu, lewzylu, channingliu
Author-email: dutie123@qq.com
License: MIT
Platform: UNKNOWN
Requires-Dist: certifi (<=2021.10.8)
Requires-Dist: requests (<=2.27.1,>=2.8)
Requires-Dist: xmltodict
Requires-Dist: six
Requires-Dist: crcmod
Requires-Dist: pycryptodome
